Workbook

Sheet Hypothèses
A1: FORGE — MODÈLE FINANCIER SAAS B2B INDUSTRIEL
A2: Tarification MySifa · Hypothèses modifiables (valeurs en bleu)
A4: A · Abonnements mensuels (HT)
A5: Essentiel | B5: 150 | C5: €/mois | D5: Hébergement + mises à jour sécu + support email 48h
A6: Suivi | B6: 280 | C6: €/mois | D6: Essentiel + corrections + ≤2h évolutions/mois (le + courant)
A7: Partenaire | B7: 490 | C7: €/mois | D7: Suivi + ≤6h évolutions/mois + réunion mensuelle
A9: B · Forfaits mise en place (one-shot, HT)
A10: Starter (1-2 modules, < 30 users) | B10: 3000 | C10: € moy. | D10: Fourchette 2 500 – 4 000 €
A11: Standard (3-5 modules, 30-100 users) | B11: 5500 | C11: € moy. | D11: Fourchette 4 000 – 7 000 €
A12: Sur mesure (ERP, > 100 users) | B12: 11000 | C12: € moy. | D12: Fourchette 7 000 – 15 000 €
A14: C · Régie / développements additionnels
A15: Tarif journalier (TJM) | B15: 650 | C15: €/jour HT | D15: Facturation sur devis, hors abonnement
A16: Jours facturables estimés / mois | B16: 5 | C16: j/mois moy. | D16: Hors setup ; variable selon charge
A18: D · Charges mensuelles estimées
A19: Hébergement VPS (mutualisé) | B19: 150 | C19: €/mois | D19: Hetzner ou OVH — 1 VPS par client progressivement
A20: Comptabilité | B20: 200 | C20: €/mois | D20: Expert-comptable ou logiciel + conseil
A21: Assurance RC Pro | B21: 60 | C21: €/mois | D21: Obligatoire en activité digitale B2B
A22: Outils & licences (Git, monitoring…) | B22: 100 | C22: €/mois | D22: GitHub, Sentry, domaine, email pro…
A23: Divers / imprévus | B23: 90 | C23: €/mois | D23: Déplacements, formation, matériel
A24: TOTAL CHARGES FIXES | B24: =SUM(B19:B23) -> 600 | C24: €/mois | D24: Hors cotisations sociales
A26: E · Cotisations sociales estimées
A27: Statut | B27: SASU / SAS | D27: Adapter si auto-entrepreneur
A28: Taux charges sociales estimé | B28: 0.45 | D28: ~45% du salaire brut en SASU
A29: Salaire brut mensuel cible | B29: 3500 | C29: €/mois | D29: À ajuster selon prélèvement souhaité
A30: Cotisations sociales estimées | B30: =B29*B28 -> 1575 | C30: €/mois
A32: CHARGES TOTALES (fixes + sociales) | B32: =B24+B30 -> 2175 | C32: €/mois

Sheet Scénarios
A1: FORGE — COMPARAISON DES SCÉNARIOS
A2: 3 scénarios de développement · Revenus annuels et rentabilité nette estimée
B4: Objectif minimum | C4: Solo confirmé (15 clients) | D4: SaaS stable (50 clients)
B5: 10-15 clients · 500-800 €/mois | C5: 15 clients · 600 €/mois moy. | D5: 50 clients · mix tarifaire
A7: Revenus — Abonnements mensuels (MRR)
A8: · Clients Essentiel (150 €/mois) | B8: 8 | C8: 10 | D8: 35
A9: · Clients Suivi (280 €/mois) | B9: 4 | C9: 4 | D9: 12
A10: · Clients Partenaire (490 €/mois) | B10: 1 | C10: 1 | D10: 3
A11: TOTAL clients | B11: =B8+B9+B10 -> 13 | C11: =C8+C9+C10 -> 15 | D11: =D8+D9+D10 -> 50
A12: MRR (€/mois) | B12: =B8*150+B9*280+B10*490 -> 2810 | C12: =C8*150+C9*280+C10*490 -> 3110 | D12: =D8*150+D9*280+D10*490 -> 10080
A13: ARR Abonnements (×12) | B13: =B12*12 -> 33720 | C13: =C12*12 -> 37320 | D13: =D12*12 -> 120960
A15: Revenus — Setups (one-shot, estimé annuel)
A16: · Setups Starter (~3 000 € moy.) | B16: 3 | C16: 4 | D16: 15
A17: · Setups Standard (~5 500 € moy.) | B17: 1 | C17: 2 | D17: 5
A18: · Setups Sur mesure (~11 000 € moy.) | B18: 0 | C18: 0 | D18: 2
A19: TOTAL Setups / an | B19: =B16*3000+B17*5500+B18*11000 -> 14500 | C19: =C16*3000+C17*5500+C18*11000 -> 23000 | D19: =D16*3000+D17*5500+D18*11000 -> 94500
A21: Revenus — Régie & développements additionnels
A22: Jours facturés / an (@ 650 €/j) | B22: 15 | C22: 30 | D22: 50
A23: TOTAL Régie / an | B23: =B22*650 -> 9750 | C23: =C22*650 -> 19500 | D23: =D22*650 -> 32500
A25: TOTAL REVENUS ANNUELS
A26: Abonnements (ARR) | B26: =B13 -> 33720 | C26: =C13 -> 37320 | D26: =D13 -> 120960
A27: Setups | B27: =B19 -> 14500 | C27: =C19 -> 23000 | D27: =D19 -> 94500
A28: Régie | B28: =B23 -> 9750 | C28: =C23 -> 19500 | D28: =D23 -> 32500
A29: CHIFFRE D'AFFAIRES TOTAL / AN | B29: =B26+B27+B28 -> 57970 | C29: =C26+C27+C28 -> 79820 | D29: =D26+D27+D28 -> 247960
A31: Charges annuelles
A32: Charges fixes (×12 — cf. Hypothèses) | B32: =Hypothèses!B32*12 -> 26100 | C32: =Hypothèses!B32*12 -> 26100 | D32: =Hypothèses!B32*12 -> 26100
A34: RÉSULTAT
A35: RÉSULTAT BRUT / AN (avant IS) | B35: =B29-B32 -> 31870 | C35: =C29-C32 -> 53720 | D35: =D29-D32 -> 221860
A36: Marge nette estimée | B36: =IFERROR(B35/B29,0) -> 0.54976712 | C36: =IFERROR(C35/C29,0) -> 0.67301428 | D36: =IFERROR(D35/D29,0) -> 0.89474109
A38: Note : le résultat brut est avant impôt société (IS ~25%) et dividendes. Les charges sociales sur salaire sont incluses dans les charges fixes (Hypothèses!B32). Les valeurs en bleu sont modifiables directement dans ce tableau ou dans l'onglet Hypothèses.

Sheet Plan 3 ans
A1: FORGE — PROJECTION SUR 3 ANS
A2: Montée en puissance progressive — du lancement à la stabilisation SaaS
B4: Année 1 — Lancement | C4: Année 2 — Croissance | D4: Année 3 — Stabilisation | E4: Var. A2→A3
B5: Phase service — beaucoup de setup | C5: Standardisation — ARR en hausse | D5: Scalabilité — MRR dominant
A7: Portefeuille clients
A8: Clients Essentiel (150 €/mois) | B8: 4 | C8: 10 | D8: 35 | E8: =IFERROR((D8-C8)/ABS(C8),0) -> 2.5
A9: Clients Suivi (280 €/mois) | B9: 2 | C9: 4 | D9: 12 | E9: =IFERROR((D9-C9)/ABS(C9),0) -> 2
A10: Clients Partenaire (490 €/mois) | B10: 0 | C10: 1 | D10: 3 | E10: =IFERROR((D10-C10)/ABS(C10),0) -> 2
A11: TOTAL clients | B11: =B8+B9+B10 -> 6 | C11: =C8+C9+C10 -> 15 | D11: =D8+D9+D10 -> 50 | E11: =IFERROR((D8+D9+D10)/(C8+C9+C10)-1,0) -> 2.3333333
A13: Revenus récurrents (MRR / ARR)
A14: MRR (€/mois) | B14: =B8*150+B9*280+B10*490 -> 1160 | C14: =C8*150+C9*280+C10*490 -> 3110 | D14: =D8*150+D9*280+D10*490 -> 10080 | E14: =IFERROR((D8*150+D9*280+D10*490)/(C8*150+C9*280+C10*490)-1,0) -> 2.2411576
A15: ARR Abonnements (×12) | B15: =B14*12 -> 13920 | C15: =C14*12 -> 37320 | D15: =D14*12 -> 120960 | E15: =IFERROR((D14*12)/(C14*12)-1,0) -> 2.2411576
A17: Revenus one-shot — Setups
A18: Setups Starter (× 3 000 € moy.) | B18: 5 | C18: 8 | D18: 15 | E18: =IFERROR((D18-C18)/ABS(C18),0) -> 0.875
A19: Setups Standard (× 5 500 € moy.) | B19: 2 | C19: 3 | D19: 6 | E19: =IFERROR((D19-C19)/ABS(C19),0) -> 1
A20: Setups Sur mesure (× 11 000 € moy.) | B20: 0 | C20: 1 | D20: 2 | E20: =IFERROR((D20-C20)/ABS(C20),0) -> 1
A21: TOTAL Setups / an | B21: =B18*3000+B19*5500+B20*11000 -> 26000 | C21: =C18*3000+C19*5500+C20*11000 -> 51500 | D21: =D18*3000+D19*5500+D20*11000 -> 100000 | E21: =IFERROR((D18*3000+D19*5500+D20*11000)/(C18*3000+C19*5500+C20*11000)-1,0) -> 0.94174757
A23: Régie & développements additionnels
A24: Jours régie facturés / an (650 €/j) | B24: 20 | C24: 35 | D24: 55 | E24: =IFERROR((D24-C24)/ABS(C24),0) -> 0.57142857
A25: TOTAL Régie / an | B25: =B24*650 -> 13000 | C25: =C24*650 -> 22750 | D25: =D24*650 -> 35750 | E25: =IFERROR((D24*650)/(C24*650)-1,0) -> 0.57142857
A27: CHIFFRE D'AFFAIRES TOTAL
A28: Abonnements (ARR) | B28: =B15 -> 13920 | C28: =C15 -> 37320 | D28: =D15 -> 120960 | E28: =IFERROR((D15)/(C15)-1,0) -> 2.2411576
A29: Setups | B29: =B21 -> 26000 | C29: =C21 -> 51500 | D29: =D21 -> 100000 | E29: =IFERROR((D21)/(C21)-1,0) -> 0.94174757
A30: Régie | B30: =B25 -> 13000 | C30: =C25 -> 22750 | D30: =D25 -> 35750 | E30: =IFERROR((D25)/(C25)-1,0) -> 0.57142857
A31: CA TOTAL / AN | B31: =B28+B29+B30 -> 52920 | C31: =C28+C29+C30 -> 111570 | D31: =D28+D29+D30 -> 256710 | E31: =IFERROR((D28+D29+D30)/(C28+C29+C30)-1,0) -> 1.3008873
A33: Charges annuelles
A34: Charges fixes + sociales (×12) | B34: =Hypothèses!B32*12 -> 26100 | C34: =Hypothèses!B32*12 -> 26100 | D34: =Hypothèses!B32*12 -> 26100 | E34: =IFERROR((Hypothèses!B32*12)/(Hypothèses!B32*12)-1,0) -> 0
A35: dont : hébergement (croissance clients) | B35: =(B8+B9+B10)*100 -> 600 | C35: =(C8+C9+C10)*100 -> 1500 | D35: =(D8+D9+D10)*100 -> 5000 | E35: =IFERROR((D35-C35)/ABS(C35),0) -> 2.3333333
A36: TOTAL CHARGES / AN | B36: =B34+B35 -> 26700 | C36: =C34+C35 -> 27600 | D36: =D34+D35 -> 31100 | E36: =IFERROR((D34+D35)/(C34+C35)-1,0) -> 0.12681159
A38: RÉSULTAT
A39: RÉSULTAT BRUT / AN (avant IS) | B39: =B31-B36 -> 26220 | C39: =C31-C36 -> 83970 | D39: =D31-D36 -> 225610 | E39: =IFERROR((D31-D36)/(C31-C36)-1,0) -> 1.6867929
A40: Marge nette | B40: =IFERROR(B39/B31,0) -> 0.49546485 | C40: =IFERROR(C39/C31,0) -> 0.75262167 | D40: =IFERROR(D39/D31,0) -> 0.87885162 | E40: =IFERROR((IFERROR(D39/D31,0))/(IFERROR(C39/C31,0))-1,0) -> 0.16772032
A41: % revenus récurrents (ARR/CA) | B41: =IFERROR(B15/B31,0) -> 0.26303855 | C41: =IFERROR(C15/C31,0) -> 0.33449852 | D41: =IFERROR(D15/D31,0) -> 0.47119318 | E41: =IFERROR((IFERROR(D15/D31,0))/(IFERROR(C15/C31,0))-1,0) -> 0.40865548
A43: Année 1 : phase service — les setups financent le lancement et construisent la base clients. Année 2 : l'ARR dépasse les charges fixes — le modèle devient rentable sans setup. Année 3 : l'ARR couvre 60-70%+ du CA — stabilisation SaaS réelle.

Sheet Grille tarifaire
A1: FORGE — GRILLE TARIFAIRE OFFICIELLE
A2: Référence commerciale · À utiliser pour les propositions clients
A4: A · Abonnements mensuels (HT) — revenu récurrent
A5: Offre | B5: Tarif HT | C5: Contenu | D5: Inclus
A6: Essentiel | B6: 150 €/mois | C6: Hébergement VPS dédié | D6: Mises à jour sécurité · Support email 48h
A7: Suivi ★ le plus courant | B7: 280 €/mois | C7: Essentiel + corrections bugs | D7: ≤ 2h évolutions/mois · Support prioritaire
A8: Partenaire | B8: 490 €/mois | C8: Suivi + évolutions régulières | D8: ≤ 6h/mois · Réunion mensuelle · Roadmap partagée
A10: B · Forfaits mise en place (one-shot, HT)
A11: Niveau | B11: Tarif moyen | C11: Fourchette | D11: Contexte
A12: Starter | B12: 3 000 € | C12: 2 500 – 4 000 € | D12: 1-2 modules · < 30 utilisateurs · process simple
A13: Standard | B13: 5 500 € | C13: 4 000 – 7 000 € | D13: 3-5 modules · 30-100 utilisateurs · workflows métier
A14: Sur mesure | B14: 11 000 € | C14: 7 000 – 15 000 € | D14: Intégration ERP · > 100 utilisateurs · logique complexe
A15: Inclus dans tout setup : audit des besoins · conception · développement · déploiement · formation initiale
A17: C · Régie / développements additionnels
A18: Tarif journalier (TJM) | B18: 650 €/jour HT | C18: ≈ 85 €/heure | D18: Facturation sur devis · hors forfait abonnement
A20: Règle commerciale : toujours présenter setup ET abonnement ensemble. Ne jamais communiquer les tarifs sans avoir qualifié le besoin. L'abonnement inclut un hébergement dédié — pas de SaaS mutualisé. Positionnement : tarif PME — pas un budget grand compte. Contact : Eugène Leconte · Forge · eugeneleconte@outlook.com · Lille / Hauts-de-France
